Workbook

Sheet Dashboard
B2: E-commerce Sales Dashboard 2025
B3: Sample project by Aman Nadeem. Pick a region or category and everything updates.
B5: Region | C5: All | F5: Category | G5: All | I5: Click the orange cells to filter
B8: Net Revenue | D8: Gross Profit | F8: Gross Margin | H8: Orders | J8: Avg Order Value | L8: Return Rate
B9: =SUMIFS(Data!$K$2:$K$901,Data!$M$2:$M$901,"Delivered",Data!$E$2:$E$901,Summary!$B$1,Data!$F$2:$F$901,Summary!$B$2) -> 46360 | D9: =SUMIFS(Data!$L$2:$L$901,Data!$M$2:$M$901,"Delivered",Data!$E$2:$E$901,Summary!$B$1,Data!$F$2:$F$901,Summary!$B$2) -> 27863 | F9: =IFERROR(SUMIFS(Data!$L$2:$L$901,Data!$M$2:$M$901,"Delivered",Data!$E$2:$E$901,Summary!$B$1,Data!$F$2:$F$901,Summary!$B$2)/SUMIFS(Data!$K$2:$K$901,Data!$M$2:$M$901,"Delivered",Data!$E$2:$E$901,Summary!$B$1,Data!$F$2:$F$901,Summary!$B$2),0) -> 0.60101381 | H9: =COUNTIFS(Data!$M$2:$M$901,"Delivered",Data!$E$2:$E$901,Summary!$B$1,Data!$F$2:$F$901,Summary!$B$2) -> 845 | J9: =IFERROR(SUMIFS(Data!$K$2:$K$901,Data!$M$2:$M$901,"Delivered",Data!$E$2:$E$901,Summary!$B$1,Data!$F$2:$F$901,Summary!$B$2)/COUNTIFS(Data!$M$2:$M$901,"Delivered",Data!$E$2:$E$901,Summary!$B$1,Data!$F$2:$F$901,Summary!$B$2),0) -> 54.863905 | L9: =IFERROR(COUNTIFS(Data!$M$2:$M$901,"Returned",Data!$E$2:$E$901,Summary!$B$1,Data!$F$2:$F$901,Summary!$B$2)/COUNTIFS(Data!$A$2:$A$901,"<>",Data!$E$2:$E$901,Summary!$B$1,Data!$F$2:$F$901,Summary!$B$2),0) -> 0.061111111
B47: Sample data is randomly generated for demonstration. Formulas power every number and chart. Built in Excel by Aman Nadeem.

Sheet Cleaning Log
B2: Data cleaning log
B3: What was wrong with the raw export and what I did about it. Sample data, generated for demonstration.
B5: Issue found | C5: Rows affected | D5: Fix applied
B6: Rows in raw export | C6: =COUNTA('Raw Data'!A:A)-1 -> 945 | D6: Starting point
B7: Duplicate orders | C7: 45 | D7: Removed, keeping one row per Order ID
B8: Dates stored as mixed text formats | C8: 703 | D8: Converted every date to a true Excel date
B9: Inconsistent capitalization and spaces in text | C9: 518 | D9: Trimmed and standardized region, category and status
B10: Prices stored as text with a $ sign | C10: 221 | D10: Converted to numbers
B11: Missing customer names | C11: 36 | D11: Kept the order (revenue still counts) and flagged the gap
B12: Rows in clean data | C12: =COUNTA(Data!A:A)-1 -> 900 | D12: Ready for analysis
B13: Rows removed | C13: =C6-C12 -> 45 | D13: Duplicates only. No valid order was deleted
B15: Note: issue counts were recorded while cleaning the raw sheet and typed in as values. Row counts are live formulas.

Sheet Raw Data
A1: order id | B1: date | C1: customer | D1: region | E1: category | F1: product | G1: qty | H1: price | I1: status
A2: ORD-10360 | B2: 17-06-25 | C2: Omar Wilson | D2: USA | E2: Beauty | F2: Face Roller | G2: 2 | H2: 18 | I2: Delivered
A3: ORD-10001 | B3: 45658 | C3: Adam Wilson | D3: Canada | E3: Home | F3: LED Desk Lamp | G3: 1 | H3: 38 | I3: Delivered
A4: ORD-10395 | B4: 01 Jul 2025 | C4: Liam Ali | D4: Canada | E4: fashion | F4: Sunglasses | G4: 1 | H4: 35 | I4: Delivered
A5: ORD-10654 | B5: 2025-10-12 | C5: Ayesha Ali | D5: UAE | E5: FASHION | F5: Leather Wallet | G5: 1 | H5: 45 | I5: Delivered
A6: ORD-10658 | B6: 45945 | C6: Sam Butt | D6: UK | E6: Home | F6: Scented Candle Set | G6: 1 | H6: 24 | I6: Delivered
A7: ORD-10686 | B7: 24-10-25 | C7: Emma Moore | D7: Canada | E7: Home | F7: Kitchen Organizer | G7: 2 | H7: $32.00 | I7: Delivered
A8: ORD-10448 | B8: 22 Jul 2025 | C8: Sana Rana | D8: USA | E8: Fashion | F8: Canvas Tote | G8: 1 | H8: 22 | I8: Delivered
A9: ORD-10427 | B9: 2025-07-11 | C9: Ayesha Ali | D9: Canada | E9: Home | F9: Scented Candle Set | G9: 1 | H9: 24 | I9: Delivered
A10: ORD-10033 | B10: 45673 | C10: Liam Hussain | D10: CANADA | E10: Fashion | F10: Sunglasses | G10: 1 | H10: $35.00 | I10: Delivered
A11: ORD-10626 | B11: 2025-10-04 | C11: Sara Taylor | D11: USA | E11: Electronics | F11: Phone Stand | G11: 1 | H11: $15.00 | I11: Delivered
A12: ORD-10819 | B12: 08 Dec 2025 | C12: Noah Ali | D12: USA | E12: Fashion | F12: Sunglasses | G12: 1 | H12: $35.00 | I12: Delivered
A13: ORD-10164 | B13: 2025-03-24 | C13: Hassan Malik | D13: USA | E13: Beauty | F13: Face Roller | G13: 1 | H13: 18 | I13: Delivered
A14: ORD-10484 | B14: 08 Aug 2025 | C14: Ben Davis | D14: USA | E14: Electronics | F14: Wireless Earbuds | G14: 1 | H14: 49 | I14: Delivered
A15: ORD-10603 | B15: 2025-09-25 | C15: Ryan Rana | D15: Australia | E15: Fitness | F15: Resistance Bands | G15: 1 | H15: 16 | I15: Returned
A16: ORD-10035 | B16: 16-01-25 | C16: Hassan Butt | D16: Canada | E16: Beauty | F16: Vitamin C Serum | G16: 1 | H16: 28 | I16: Delivered
A17: ORD-10279 | B17: 05/15/2025 | C17: Hina Wilson | D17: USA | E17: Fitness | F17: Water Bottle | G17: 1 | H17: $21.00 | I17: Delivered
A18: ORD-10420 | B18: 09 Jul 2025 | C18: Ella Rana | D18: UK | E18: Electronics | F18: Wireless Earbuds | G18: 1 | H18: $49.00 | I18: Delivered
A19: ORD-10310 | B19: 26-05-25 | C19: Lucy Malik | D19: Canada | E19: Fashion | F19: Leather Wallet | G19: 2 | H19: 45 | I19: Delivered
A20: ORD-10146 | B20: 03/14/2025 | C20: Sana Rana | D20: USA | E20: Fitness | F20: Water Bottle | G20: 1 | H20: 21 | I20: Delivered
A21: ORD-10478 | B21: 06-08-25 | C21: Nora Taylor | D21: Australia | E21: Fashion | F21: Leather Wallet | G21: 1 | H21: $45.00 | I21: DELIVERED
A22: ORD-10378 | B22: 23-06-25 | C22: Noah Davis | D22: UK | E22: electronics | F22: Wireless Earbuds | G22: 2 | H22: 49 | I22: Delivered
A23: ORD-10125 | B23: 04 Mar 2025 | C23: Lucy Ali | D23: UAE | E23: Beauty | F23: Hair Dryer | G23: 1 | H23: 54 | I23: Delivered
A24: ORD-10283 | B24: 2025-05-17 | C24: Sara Ali | D24: Canada | E24: Fashion | F24: Leather Wallet | G24: 1 | H24: 45 | I24: Delivered
A25: ORD-10657 | B25: 15 Oct 2025 | C25: Omar Moore | D25: USA | E25: Beauty | F25: Vitamin C Serum | G25: 1 | H25: 28 | I25: Delivered
A26: ORD-10400 | B26: 45839 | C26: Hassan Malik | D26: UK | E26: Electronics | F26: Phone Stand | G26: 2 | H26: 15 | I26: Delivered
A27: ORD-10695 | B27: 45963 | C27: Ella Malik | D27: USA | E27: Fashion | F27: Canvas Tote | G27: 1 | H27: $22.00 | I27: Delivered
A28: ORD-10575 | B28: 45915 | C28: Ali Taylor | D28: usa | E28: Fitness | F28: Resistance Bands | G28: 2 | H28: 16 | I28: Delivered
A29: ORD-10290 | B29: 19-05-25 | C29: Ben Davis | D29: USA | E29: Electronics | F29: Wireless Earbuds | G29: 1 | H29: 49 | I29: Returned
A30: ORD-10619 | B30: 45931 | C30: Zara Davis | D30: USA | E30: Beauty | F30: Vitamin C Serum | G30: 1 | H30: $28.00 | I30: Delivered
A31: ORD-10791 | B31: 2025-11-28 | C31: Sara Ahmed | D31: UK | E31: HOME | F31: Kitchen Organizer | G31: 1 | H31: 32 | I31: Delivered
A32: ORD-10278 | B32: 05/14/2025 | C32: Ayesha Shah | D32: USA | E32: Fashion | F32: Sunglasses | G32: 1 | H32: 35 | I32: Delivered
A33: ORD-10235 | B33: 27 Apr 2025 | C33: Nora Butt | D33: UK | E33: Home | F33: Scented Candle Set | G33: 1 | H33: 24 | I33: Delivered
A34: ORD-10246 | B34: 2025-05-02 | C34: Sana Hussain | D34: USA | E34: Fashion | F34: Leather Wallet | G34: 2 | H34: $45.00 | I34: Delivered
A35: ORD-10532 | B35: 26-08-25 | D35: USA | E35: Beauty | F35: Face Roller | G35: 1 | H35: $18.00 | I35: Delivered
A36: ORD-10802 | B36: 12/04/2025 | C36: Sana Moore | D36: CANADA | E36: Electronics | F36: Phone Stand | G36: 1 | H36: $15.00 | I36: Delivered
A37: ORD-10595 | B37: 23-09-25 | C37: Sam Smith | D37: Australia | E37: Fashion | F37: Leather Wallet | G37: 1 | H37: 45 | I37: Delivered
A38: ORD-10277 | B38: 14-05-25 | C38: Omar Ahmed | D38: Canada | E38: Beauty | F38: Hair Dryer | G38: 1 | H38: 54 | I38: Delivered
A39: ORD-10244 | B39: 05/01/2025 | C39: Hina Davis | D39: UAE | E39: Fashion | F39: Leather Wallet | G39: 2 | H39: 45 | I39: Delivered
A40: ORD-10861 | B40: 19-12-25 | C40: Sam Davis | D40: UK | E40: Electronics | F40: Smart Watch | G40: 1 | H40: 89 | I40: Delivered
A41: ORD-10236 | B41: 27-04-25 | C41: Sara Ali | D41: UK | E41: Fashion | F41: Leather Wallet | G41: 1 | H41: 45 | I41: delivered
A42: ORD-10868 | B42: 20-12-25 | C42: Emma Moore | D42: Canada | E42: Home | F42: LED Desk Lamp | G42: 2 | H42: 38 | I42: Delivered
A43: ORD-10187 | B43: 04/02/2025 | C43: Omar Ahmed | D43: USA | E43: Electronics | F43: Smart Watch | G43: 1 | H43: 89 | I43: delivered
A44: ORD-10746 | B44: 11/15/2025 | C44: Hassan Malik | D44: UAE | E44: Electronics | F44: Wireless Earbuds | G44: 1 | H44: 49 | I44: Delivered
A45: ORD-10504 | B45: 13-08-25 | C45: Sana Clark | D45: USA | E45: Home | F45: Kitchen Organizer | G45: 3 | H45: $32.00 | I45: Returned
A46: ORD-10486 | B46: 08/09/2025 | C46: Ayesha Shah | D46: USA | E46: Beauty | F46: Vitamin C Serum | G46: 1 | H46: 28 | I46: Delivered
A47: ORD-10227 | B47: 45770 | C47: Sam Ahmed | D47: Canada | E47: HOME | F47: Kitchen Organizer | G47: 1 | H47: $32.00 | I47: Delivered
A48: ORD-10419 | B48: 45846 | C48: Adam Khan | D48: UK | E48: Home | F48: Kitchen Organizer | G48: 1 | H48: 32 | I48: Delivered
A49: ORD-10590 | B49: 09/21/2025 | C49: Mia Malik | D49: Canada | E49: Electronics | F49: Smart Watch | G49: 3 | H49: $89.00 | I49: Delivered
A50: ORD-10648 | B50: 45942 | C50: Noah Ali | D50: Australia | E50: Fashion | F50: Sunglasses | G50: 1 | H50: 35 | I50: Delivered
A51: ORD-10899 | B51: 46019 | C51: Adam Smith | D51: UAE | E51: Fashion | F51: Canvas Tote | G51: 1 | H51: 22 | I51: delivered
A52: ORD-10472 | B52: 08/04/2025 | C52: Hassan Taylor | D52: USA | E52: BEAUTY | F52: Hair Dryer | G52: 1 | H52: $54.00 | I52: Delivered
A53: ORD-10513 | B53: 18 Aug 2025 | C53: Adam Smith | D53: USA | E53: Beauty | F53: Vitamin C Serum | G53: 1 | H53: 28 | I53: Delivered
A54: ORD-10875 | B54: 46012 | C54: Jack Butt | D54: USA | E54: Fashion | F54: Canvas Tote | G54: 2 | H54: 22 | I54: Delivered
A55: ORD-10251 | B55: 45781 | C55: Sana Clark | D55: USA | E55: Fitness | F55: Yoga Mat | G55: 2 | H55: 30 | I55: Delivered
A56: ORD-10463 | B56: 01-08-25 | C56: Ali Rana | D56: USA | E56: Electronics | F56: Wireless Earbuds | G56: 1 | H56: 49 | I56: Delivered
A57: ORD-10216 | B57: 45765 | C57: Adam Ahmed | D57: Canada | E57: Fitness | F57: Yoga Mat | G57: 3 | H57: $30.00 | I57: Delivered
A58: ORD-10368 | B58: 2025-06-18 | C58: Ali Moore | D58: USA | E58: Electronics | F58: Phone Stand | G58: 1 | H58: 15 | I58: Delivered
A59: ORD-10466 | B59: 2025-08-02 | C59: Noah Hussain | D59: USA | E59: Fitness | F59: Resistance Bands | G59: 1 | H59: 16 | I59: Delivered
A60: ORD-10302 | B60: 45801 | C60: Lucy Young | D60: USA | E60: Fashion | F60: Canvas Tote | G60: 2 | H60: $22.00 | I60: Delivered
A61: ORD-10362 | B61: 17 Jun 2025 | C61: Ayesha Shah | D61: AUSTRALIA | E61: Electronics | F61: Smart Watch | G61: 2 | H61: 89 | I61: Delivered
A62: ORD-10514 | B62: 08/19/2025 | C62: Ayesha Shah | D62: UK | E62: Home | F62: Scented Candle Set | G62: 1 | H62: 24 | I62: Delivered
A63: ORD-10143 | B63: 12-03-25 | C63: Zara Khan | D63: UAE | E63: Home | F63: LED Desk Lamp | G63: 3 | H63: $38.00 | I63: Delivered
A64: ORD-10822 | B64: 09 Dec 2025 | C64: Ryan Clark | D64: USA | E64: Electronics | F64: Wireless Earbuds | G64: 1 | H64: $49.00 | I64: Delivered
A65: ORD-10439 | B65: 19-07-25 | C65: Hina Wilson | D65: Canada | E65: Fashion | F65: Canvas Tote | G65: 1 | H65: 22 | I65: Delivered
A66: ORD-10458 | B66: 2025-07-27 | C66: Zara Davis | D66: UAE | E66: Electronics | F66: Wireless Earbuds | G66: 1 | H66: 49 | I66: DELIVERED
A67: ORD-10845 | B67: 14 Dec 2025 | C67: Sam Clark | D67: USA | E67: Beauty | F67: Face Roller | G67: 1 | H67: 18 | I67: Delivered
A68: ORD-10063 | B68: 28 Jan 2025 | C68: Sara Brown | D68: Australia | E68: Home | F68: Kitchen Organizer | G68: 2 | H68: $32.00 | I68: Delivered
A69: ORD-10799 | B69: 45994 | C69: Adam Ahmed | D69: UK | E69: Home | F69: LED Desk Lamp | G69: 1 | H69: 38 | I69: Delivered
A70: ORD-10790 | B70: 28 Nov 2025 | C70: Ayesha Ali | D70: Australia | E70: Fashion | F70: Sunglasses | G70: 2 | H70: $35.00 | I70: Delivered
A71: ORD-10476 | B71: 05 Aug 2025 | C71: Jack Smith | D71: USA | E71: Beauty | F71: Face Roller | G71: 1 | H71: $18.00 | I71: Delivered
A72: ORD-10046 | B72: 01/21/2025 | C72: Mia Smith | D72: USA | E72: Home | F72: Kitchen Organizer | G72: 1 | H72: 32 | I72: Delivered
A73: ORD-10503 | B73: 45882 | C73: Adam Smith | D73: UK | E73: Fashion | F73: Leather Wallet | G73: 2 | H73: 45 | I73: Delivered
A74: ORD-10295 | B74: 05/20/2025 | C74: Omar Malik | D74: australia | E74: Home | F74: Kitchen Organizer | G74: 1 | H74: 32 | I74: Returned
A75: ORD-10477 | B75: 06 Aug 2025 | C75: Ben Moore | D75: USA | E75: home | F75: Scented Candle Set | G75: 2 | H75: $24.00 | I75: Delivered
A76: ORD-10023 | B76: 12-01-25 | C76: Sana Wilson | D76: USA | E76: fitness | F76: Resistance Bands | G76: 1 | H76: 16 | I76: Delivered
A77: ORD-10234 | B77: 04/27/2025 | C77: Hina Young | D77: uk | E77: Fashion | F77: Leather Wallet | G77: 1 | H77: 45 | I77: Delivered
A78: ORD-10574 | B78: 09/15/2025 | C78: Ryan Brown | D78: UK | E78: Fashion | F78: Sunglasses | G78: 2 | H78: 35 | I78: Delivered
A79: ORD-10289 | B79: 19-05-25 | C79: Hina Butt | D79: USA | E79: Home | F79: Scented Candle Set | G79: 1 | H79: 24 | I79: Delivered
A80: ORD-10198 | B80: 04/08/2025 | C80: Ali Rana | D80: USA | E80: Fashion | F80: Canvas Tote | G80: 3 | H80: 22 | I80: Delivered
A81: ORD-10032 | B81: 15 Jan 2025 | C81: Ayesha Ali | D81: USA | E81: Fashion | F81: Sunglasses | G81: 1 | H81: $35.00 | I81: Delivered
A82: ORD-10557 | B82: 09/05/2025 | C82: Liam Hussain | D82: Canada | E82: Beauty | F82: Hair Dryer | G82: 1 | H82: 54 | I82: Delivered
A83: ORD-10144 | B83: 45728 | C83: Sana Rana | D83: UK | E83: Fashion | F83: Canvas Tote | G83: 1 | H83: 22 | I83: Delivered
A84: ORD-10044 | B84: 21 Jan 2025 | C84: Ella Malik | D84: USA | E84: Fitness | F84: Water Bottle | G84: 1 | H84: 21 | I84: Delivered
A85: ORD-10291 | B85: 05/19/2025 | C85: Sam Wilson | D85: UK | E85: Electronics | F85: Smart Watch | G85: 1 | H85: 89 | I85: returned
A86: ORD-10261 | B86: 10-05-25 | C86: Ayesha Khan | D86: USA | E86: Electronics | F86: Smart Watch | G86: 1 | H86: 89 | I86: Delivered
A87: ORD-10257 | B87: 08-05-25 | C87: Ryan Ali | D87: usa | E87: Electronics | F87: Phone Stand | G87: 1 | H87: $15.00 | I87: Delivered
A88: ORD-10392 | B88: 28 Jun 2025 | C88: Sam Wilson | D88: UAE | E88: Fitness | F88: Resistance Bands | G88: 2 | H88: $16.00 | I88: Delivered
A89: ORD-10765 | B89: 2025-11-22 | C89: Zara Hussain | D89: USA | E89: Fashion | F89: Sunglasses | G89: 2 | H89: 35 | I89: Delivered
A90: ORD-10005 | B90: 01/02/2025 | C90: Liam Smith | D90: Australia | E90: Electronics | F90: Phone Stand | G90: 1 | H90: 15 | I90: Delivered
A91: ORD-10253 | B91: 07-05-25 | C91: Sam Moore | D91: Canada | E91: Beauty | F91: Hair Dryer | G91: 1 | H91: 54 | I91: Delivered
A92: ORD-10670 | B92: 10/21/2025 | C92: Sam Ahmed | D92: UK | E92: Beauty | F92: Hair Dryer | G92: 2 | H92: 54 | I92: Delivered
A93: ORD-10481 | B93: 08/07/2025 | C93: Sam Butt | D93: USA | E93: Electronics | F93: Phone Stand | G93: 1 | H93: 15 | I93: Delivered
A94: ORD-10501 | B94: 45882 | C94: Ryan Smith | D94: canada | E94: Fashion | F94: Canvas Tote | G94: 1 | H94: $22.00 | I94: Returned
A95: ORD-10762 | B95: 21 Nov 2025 | C95: Ella Young | D95: USA | E95: Beauty | F95: Face Roller | G95: 1 | H95: 18 | I95: Delivered
A96: ORD-10405 | B96: 07/02/2025 | C96: Ali Rana | D96: UK | E96: Home | F96: Scented Candle Set | G96: 1 | H96: 24 | I96: Delivered
A97: ORD-10617 | B97: 45931 | C97: Nora Butt | D97: USA | E97: Beauty | F97: Hair Dryer | G97: 3 | H97: 54 | I97: Delivered
A98: ORD-10089 | B98: 02/14/2025 | C98: Sam Ahmed | D98: USA | E98: Electronics | F98: Phone Stand | G98: 2 | H98: $15.00 | I98: Delivered
A99: ORD-10088 | B99: 45702 | C99: Nora Butt | D99: USA | E99: BEAUTY | F99: Vitamin C Serum | G99: 2 | H99: $28.00 | I99: Delivered
A100: ORD-10440 | B100: 19 Jul 2025 | C100: Sam Brown | D100: Australia | E100: Beauty | F100: Vitamin C Serum | G100: 1 | H100: 28 | I100: Returned
...

Sheet Data
A1: Order ID | B1: Date | C1: Month | D1: Customer | E1: Region | F1: Category | G1: Product | H1: Units | I1: Unit Price | J1: Unit Cost | K1: Revenue | L1: Profit | M1: Status
A2: ORD-10001 | B2: 45658 | C2: =MONTH(B2) -> 1 | D2: Adam Wilson | E2: Canada | F2: Home | G2: LED Desk Lamp | H2: 1 | I2: 38 | J2: 16 | K2: =H2*I2 -> 38 | L2: =K2-H2*J2 -> 22 | M2: Delivered
A3: ORD-10002 | B3: 45658 | C3: =MONTH(B3) -> 1 | D3: Liam Malik | E3: USA | F3: Home | G3: LED Desk Lamp | H3: 1 | I3: 38 | J3: 16 | K3: =H3*I3 -> 38 | L3: =K3-H3*J3 -> 22 | M3: Delivered
A4: ORD-10003 | B4: 45659 | C4: =MONTH(B4) -> 1 | D4: Emma Smith | E4: USA | F4: Fashion | G4: Leather Wallet | H4: 4 | I4: 45 | J4: 17 | K4: =H4*I4 -> 180 | L4: =K4-H4*J4 -> 112 | M4: Delivered
A5: ORD-10004 | B5: 45659 | C5: =MONTH(B5) -> 1 | D5: Mia Young | E5: USA | F5: Electronics | G5: Phone Stand | H5: 4 | I5: 15 | J5: 5 | K5: =H5*I5 -> 60 | L5: =K5-H5*J5 -> 40 | M5: Delivered
A6: ORD-10005 | B6: 45659 | C6: =MONTH(B6) -> 1 | D6: Liam Smith | E6: Australia | F6: Electronics | G6: Phone Stand | H6: 1 | I6: 15 | J6: 5 | K6: =H6*I6 -> 15 | L6: =K6-H6*J6 -> 10 | M6: Delivered
A7: ORD-10006 | B7: 45659 | C7: =MONTH(B7) -> 1 | D7: Adam Brown | E7: UAE | F7: Beauty | G7: Vitamin C Serum | H7: 1 | I7: 28 | J7: 9 | K7: =H7*I7 -> 28 | L7: =K7-H7*J7 -> 19 | M7: Delivered
A8: ORD-10007 | B8: 45659 | C8: =MONTH(B8) -> 1 | D8: Ali Taylor | E8: Canada | F8: Fashion | G8: Leather Wallet | H8: 1 | I8: 45 | J8: 17 | K8: =H8*I8 -> 45 | L8: =K8-H8*J8 -> 28 | M8: Delivered
A9: ORD-10008 | B9: 45659 | C9: =MONTH(B9) -> 1 | D9: Emma Taylor | E9: USA | F9: Fitness | G9: Resistance Bands | H9: 4 | I9: 16 | J9: 5 | K9: =H9*I9 -> 64 | L9: =K9-H9*J9 -> 44 | M9: Delivered
A10: ORD-10009 | B10: 45661 | C10: =MONTH(B10) -> 1 | D10: Mia Young | E10: USA | F10: Beauty | G10: Hair Dryer | H10: 1 | I10: 54 | J10: 24 | K10: =H10*I10 -> 54 | L10: =K10-H10*J10 -> 30 | M10: Returned
A11: ORD-10010 | B11: 45662 | C11: =MONTH(B11) -> 1 | D11: Zara Clark | E11: Canada | F11: Beauty | G11: Vitamin C Serum | H11: 1 | I11: 28 | J11: 9 | K11: =H11*I11 -> 28 | L11: =K11-H11*J11 -> 19 | M11: Delivered
A12: ORD-10011 | B12: 45664 | C12: =MONTH(B12) -> 1 | D12: Sana Smith | E12: USA | F12: Home | G12: Kitchen Organizer | H12: 1 | I12: 32 | J12: 13 | K12: =H12*I12 -> 32 | L12: =K12-H12*J12 -> 19 | M12: Delivered
A13: ORD-10012 | B13: 45664 | C13: =MONTH(B13) -> 1 | D13: Omar Shah | E13: USA | F13: Fashion | G13: Leather Wallet | H13: 1 | I13: 45 | J13: 17 | K13: =H13*I13 -> 45 | L13: =K13-H13*J13 -> 28 | M13: Delivered
... A901: ORD-10900 | B901: 46019 | C901: =MONTH(B901) -> 12 | D901: Sam Shah | E901: USA | F901: Beauty | G901: Hair Dryer | H901: 1 | I901: 54 | J901: 24 | K901: =H901*I901 -> 54 | L901: =K901-H901*J901 -> 30 | M901: Returned

Sheet Summary
A1: Region criteria | B1: =IF(Dashboard!C5="All","*",Dashboard!C5) -> *
A2: Category criteria | B2: =IF(Dashboard!G5="All","*",Dashboard!G5) -> *
A5: Month | B5: Net revenue | C5: Profit | D5: Orders | E5: Month no. | G5: Category | H5: Net revenue | K5: Region | L5: Net revenue
A6: Jan | B6: =SUMIFS(Data!$K$2:$K$901,Data!$M$2:$M$901,"Delivered",Data!$C$2:$C$901,$E6,Data!$E$2:$E$901,$B$1,Data!$F$2:$F$901,$B$2) -> 3639 | C6: =SUMIFS(Data!$L$2:$L$901,Data!$M$2:$M$901,"Delivered",Data!$C$2:$C$901,$E6,Data!$E$2:$E$901,$B$1,Data!$F$2:$F$901,$B$2) -> 2185 | D6: =COUNTIFS(Data!$M$2:$M$901,"Delivered",Data!$C$2:$C$901,$E6,Data!$E$2:$E$901,$B$1,Data!$F$2:$F$901,$B$2) -> 60 | E6: 1 | G6: Electronics | H6: =SUMIFS(Data!$K$2:$K$901,Data!$M$2:$M$901,"Delivered",Data!$F$2:$F$901,$G6,Data!$E$2:$E$901,$B$1) -> 14402 | K6: USA | L6: =SUMIFS(Data!$K$2:$K$901,Data!$M$2:$M$901,"Delivered",Data!$E$2:$E$901,$K6,Data!$F$2:$F$901,$B$2) -> 18131
A7: Feb | B7: =SUMIFS(Data!$K$2:$K$901,Data!$M$2:$M$901,"Delivered",Data!$C$2:$C$901,$E7,Data!$E$2:$E$901,$B$1,Data!$F$2:$F$901,$B$2) -> 2364 | C7: =SUMIFS(Data!$L$2:$L$901,Data!$M$2:$M$901,"Delivered",Data!$C$2:$C$901,$E7,Data!$E$2:$E$901,$B$1,Data!$F$2:$F$901,$B$2) -> 1449 | D7: =COUNTIFS(Data!$M$2:$M$901,"Delivered",Data!$C$2:$C$901,$E7,Data!$E$2:$E$901,$B$1,Data!$F$2:$F$901,$B$2) -> 52 | E7: 2 | G7: Home | H7: =SUMIFS(Data!$K$2:$K$901,Data!$M$2:$M$901,"Delivered",Data!$F$2:$F$901,$G7,Data!$E$2:$E$901,$B$1) -> 8768 | K7: UK | L7: =SUMIFS(Data!$K$2:$K$901,Data!$M$2:$M$901,"Delivered",Data!$E$2:$E$901,$K7,Data!$F$2:$F$901,$B$2) -> 8031
A8: Mar | B8: =SUMIFS(Data!$K$2:$K$901,Data!$M$2:$M$901,"Delivered",Data!$C$2:$C$901,$E8,Data!$E$2:$E$901,$B$1,Data!$F$2:$F$901,$B$2) -> 3588 | C8: =SUMIFS(Data!$L$2:$L$901,Data!$M$2:$M$901,"Delivered",Data!$C$2:$C$901,$E8,Data!$E$2:$E$901,$B$1,Data!$F$2:$F$901,$B$2) -> 2131 | D8: =COUNTIFS(Data!$M$2:$M$901,"Delivered",Data!$C$2:$C$901,$E8,Data!$E$2:$E$901,$B$1,Data!$F$2:$F$901,$B$2) -> 59 | E8: 3 | G8: Beauty | H8: =SUMIFS(Data!$K$2:$K$901,Data!$M$2:$M$901,"Delivered",Data!$F$2:$F$901,$G8,Data!$E$2:$E$901,$B$1) -> 9536 | K8: Canada | L8: =SUMIFS(Data!$K$2:$K$901,Data!$M$2:$M$901,"Delivered",Data!$E$2:$E$901,$K8,Data!$F$2:$F$901,$B$2) -> 7902
A9: Apr | B9: =SUMIFS(Data!$K$2:$K$901,Data!$M$2:$M$901,"Delivered",Data!$C$2:$C$901,$E9,Data!$E$2:$E$901,$B$1,Data!$F$2:$F$901,$B$2) -> 2728 | C9: =SUMIFS(Data!$L$2:$L$901,Data!$M$2:$M$901,"Delivered",Data!$C$2:$C$901,$E9,Data!$E$2:$E$901,$B$1,Data!$F$2:$F$901,$B$2) -> 1648 | D9: =COUNTIFS(Data!$M$2:$M$901,"Delivered",Data!$C$2:$C$901,$E9,Data!$E$2:$E$901,$B$1,Data!$F$2:$F$901,$B$2) -> 53 | E9: 4 | G9: Fashion | H9: =SUMIFS(Data!$K$2:$K$901,Data!$M$2:$M$901,"Delivered",Data!$F$2:$F$901,$G9,Data!$E$2:$E$901,$B$1) -> 9216 | K9: UAE | L9: =SUMIFS(Data!$K$2:$K$901,Data!$M$2:$M$901,"Delivered",Data!$E$2:$E$901,$K9,Data!$F$2:$F$901,$B$2) -> 6650
A10: May | B10: =SUMIFS(Data!$K$2:$K$901,Data!$M$2:$M$901,"Delivered",Data!$C$2:$C$901,$E10,Data!$E$2:$E$901,$B$1,Data!$F$2:$F$901,$B$2) -> 4135 | C10: =SUMIFS(Data!$L$2:$L$901,Data!$M$2:$M$901,"Delivered",Data!$C$2:$C$901,$E10,Data!$E$2:$E$901,$B$1,Data!$F$2:$F$901,$B$2) -> 2475 | D10: =COUNTIFS(Data!$M$2:$M$901,"Delivered",Data!$C$2:$C$901,$E10,Data!$E$2:$E$901,$B$1,Data!$F$2:$F$901,$B$2) -> 70 | E10: 5 | G10: Fitness | H10: =SUMIFS(Data!$K$2:$K$901,Data!$M$2:$M$901,"Delivered",Data!$F$2:$F$901,$G10,Data!$E$2:$E$901,$B$1) -> 4438 | K10: Australia | L10: =SUMIFS(Data!$K$2:$K$901,Data!$M$2:$M$901,"Delivered",Data!$E$2:$E$901,$K10,Data!$F$2:$F$901,$B$2) -> 5646
A11: Jun | B11: =SUMIFS(Data!$K$2:$K$901,Data!$M$2:$M$901,"Delivered",Data!$C$2:$C$901,$E11,Data!$E$2:$E$901,$B$1,Data!$F$2:$F$901,$B$2) -> 4412 | C11: =SUMIFS(Data!$L$2:$L$901,Data!$M$2:$M$901,"Delivered",Data!$C$2:$C$901,$E11,Data!$E$2:$E$901,$B$1,Data!$F$2:$F$901,$B$2) -> 2641 | D11: =COUNTIFS(Data!$M$2:$M$901,"Delivered",Data!$C$2:$C$901,$E11,Data!$E$2:$E$901,$B$1,Data!$F$2:$F$901,$B$2) -> 79 | E11: 6
A12: Jul | B12: =SUMIFS(Data!$K$2:$K$901,Data!$M$2:$M$901,"Delivered",Data!$C$2:$C$901,$E12,Data!$E$2:$E$901,$B$1,Data!$F$2:$F$901,$B$2) -> 2876 | C12: =SUMIFS(Data!$L$2:$L$901,Data!$M$2:$M$901,"Delivered",Data!$C$2:$C$901,$E12,Data!$E$2:$E$901,$B$1,Data!$F$2:$F$901,$B$2) -> 1732 | D12: =COUNTIFS(Data!$M$2:$M$901,"Delivered",Data!$C$2:$C$901,$E12,Data!$E$2:$E$901,$B$1,Data!$F$2:$F$901,$B$2) -> 61 | E12: 7
A13: Aug | B13: =SUMIFS(Data!$K$2:$K$901,Data!$M$2:$M$901,"Delivered",Data!$C$2:$C$901,$E13,Data!$E$2:$E$901,$B$1,Data!$F$2:$F$901,$B$2) -> 4419 | C13: =SUMIFS(Data!$L$2:$L$901,Data!$M$2:$M$901,"Delivered",Data!$C$2:$C$901,$E13,Data!$E$2:$E$901,$B$1,Data!$F$2:$F$901,$B$2) -> 2629 | D13: =COUNTIFS(Data!$M$2:$M$901,"Delivered",Data!$C$2:$C$901,$E13,Data!$E$2:$E$901,$B$1,Data!$F$2:$F$901,$B$2) -> 72 | E13: 8
A14: Sep | B14: =SUMIFS(Data!$K$2:$K$901,Data!$M$2:$M$901,"Delivered",Data!$C$2:$C$901,$E14,Data!$E$2:$E$901,$B$1,Data!$F$2:$F$901,$B$2) -> 3685 | C14: =SUMIFS(Data!$L$2:$L$901,Data!$M$2:$M$901,"Delivered",Data!$C$2:$C$901,$E14,Data!$E$2:$E$901,$B$1,Data!$F$2:$F$901,$B$2) -> 2243 | D14: =COUNTIFS(Data!$M$2:$M$901,"Delivered",Data!$C$2:$C$901,$E14,Data!$E$2:$E$901,$B$1,Data!$F$2:$F$901,$B$2) -> 73 | E14: 9
A15: Oct | B15: =SUMIFS(Data!$K$2:$K$901,Data!$M$2:$M$901,"Delivered",Data!$C$2:$C$901,$E15,Data!$E$2:$E$901,$B$1,Data!$F$2:$F$901,$B$2) -> 4236 | C15: =SUMIFS(Data!$L$2:$L$901,Data!$M$2:$M$901,"Delivered",Data!$C$2:$C$901,$E15,Data!$E$2:$E$901,$B$1,Data!$F$2:$F$901,$B$2) -> 2521 | D15: =COUNTIFS(Data!$M$2:$M$901,"Delivered",Data!$C$2:$C$901,$E15,Data!$E$2:$E$901,$B$1,Data!$F$2:$F$901,$B$2) -> 72 | E15: 10
A16: Nov | B16: =SUMIFS(Data!$K$2:$K$901,Data!$M$2:$M$901,"Delivered",Data!$C$2:$C$901,$E16,Data!$E$2:$E$901,$B$1,Data!$F$2:$F$901,$B$2) -> 5262 | C16: =SUMIFS(Data!$L$2:$L$901,Data!$M$2:$M$901,"Delivered",Data!$C$2:$C$901,$E16,Data!$E$2:$E$901,$B$1,Data!$F$2:$F$901,$B$2) -> 3188 | D16: =COUNTIFS(Data!$M$2:$M$901,"Delivered",Data!$C$2:$C$901,$E16,Data!$E$2:$E$901,$B$1,Data!$F$2:$F$901,$B$2) -> 95 | E16: 11
A17: Dec | B17: =SUMIFS(Data!$K$2:$K$901,Data!$M$2:$M$901,"Delivered",Data!$C$2:$C$901,$E17,Data!$E$2:$E$901,$B$1,Data!$F$2:$F$901,$B$2) -> 5016 | C17: =SUMIFS(Data!$L$2:$L$901,Data!$M$2:$M$901,"Delivered",Data!$C$2:$C$901,$E17,Data!$E$2:$E$901,$B$1,Data!$F$2:$F$901,$B$2) -> 3021 | D17: =COUNTIFS(Data!$M$2:$M$901,"Delivered",Data!$C$2:$C$901,$E17,Data!$E$2:$E$901,$B$1,Data!$F$2:$F$901,$B$2) -> 99 | E17: 12
A21: Product | B21: Category | C21: Net revenue | D21: Rank helper | G21: Rank | H21: Top products | I21: Net revenue
A22: Wireless Earbuds | B22: Electronics | C22: =SUMIFS(Data!$K$2:$K$901,Data!$M$2:$M$901,"Delivered",Data!$G$2:$G$901,$A22,Data!$E$2:$E$901,$B$1,Data!$F$2:$F$901,$B$2) -> 5145 | D22: =C22+ROW()/1000000 -> 5145 | G22: 1 | H22: =INDEX($A$22:$A$36,MATCH(LARGE($D$22:$D$36,G22),$D$22:$D$36,0)) -> Smart Watch | I22: =INDEX($C$22:$C$36,MATCH(LARGE($D$22:$D$36,G22),$D$22:$D$36,0)) -> 7832
A23: Smart Watch | B23: Electronics | C23: =SUMIFS(Data!$K$2:$K$901,Data!$M$2:$M$901,"Delivered",Data!$G$2:$G$901,$A23,Data!$E$2:$E$901,$B$1,Data!$F$2:$F$901,$B$2) -> 7832 | D23: =C23+ROW()/1000000 -> 7832 | G23: 2 | H23: =INDEX($A$22:$A$36,MATCH(LARGE($D$22:$D$36,G23),$D$22:$D$36,0)) -> Hair Dryer | I23: =INDEX($C$22:$C$36,MATCH(LARGE($D$22:$D$36,G23),$D$22:$D$36,0)) -> 5562
A24: Phone Stand | B24: Electronics | C24: =SUMIFS(Data!$K$2:$K$901,Data!$M$2:$M$901,"Delivered",Data!$G$2:$G$901,$A24,Data!$E$2:$E$901,$B$1,Data!$F$2:$F$901,$B$2) -> 1425 | D24: =C24+ROW()/1000000 -> 1425 | G24: 3 | H24: =INDEX($A$22:$A$36,MATCH(LARGE($D$22:$D$36,G24),$D$22:$D$36,0)) -> Wireless Earbuds | I24: =INDEX($C$22:$C$36,MATCH(LARGE($D$22:$D$36,G24),$D$22:$D$36,0)) -> 5145
A25: Scented Candle Set | B25: Home | C25: =SUMIFS(Data!$K$2:$K$901,Data!$M$2:$M$901,"Delivered",Data!$G$2:$G$901,$A25,Data!$E$2:$E$901,$B$1,Data!$F$2:$F$901,$B$2) -> 2088 | D25: =C25+ROW()/1000000 -> 2088 | G25: 4 | H25: =INDEX($A$22:$A$36,MATCH(LARGE($D$22:$D$36,G25),$D$22:$D$36,0)) -> Leather Wallet | I25: =INDEX($C$22:$C$36,MATCH(LARGE($D$22:$D$36,G25),$D$22:$D$36,0)) -> 4230
A26: Kitchen Organizer | B26: Home | C26: =SUMIFS(Data!$K$2:$K$901,Data!$M$2:$M$901,"Delivered",Data!$G$2:$G$901,$A26,Data!$E$2:$E$901,$B$1,Data!$F$2:$F$901,$B$2) -> 2880 | D26: =C26+ROW()/1000000 -> 2880 | G26: 5 | H26: =INDEX($A$22:$A$36,MATCH(LARGE($D$22:$D$36,G26),$D$22:$D$36,0)) -> LED Desk Lamp | I26: =INDEX($C$22:$C$36,MATCH(LARGE($D$22:$D$36,G26),$D$22:$D$36,0)) -> 3800
A27: LED Desk Lamp | B27: Home | C27: =SUMIFS(Data!$K$2:$K$901,Data!$M$2:$M$901,"Delivered",Data!$G$2:$G$901,$A27,Data!$E$2:$E$901,$B$1,Data!$F$2:$F$901,$B$2) -> 3800 | D27: =C27+ROW()/1000000 -> 3800
A28: Vitamin C Serum | B28: Beauty | C28: =SUMIFS(Data!$K$2:$K$901,Data!$M$2:$M$901,"Delivered",Data!$G$2:$G$901,$A28,Data!$E$2:$E$901,$B$1,Data!$F$2:$F$901,$B$2) -> 2660 | D28: =C28+ROW()/1000000 -> 2660
A29: Hair Dryer | B29: Beauty | C29: =SUMIFS(Data!$K$2:$K$901,Data!$M$2:$M$901,"Delivered",Data!$G$2:$G$901,$A29,Data!$E$2:$E$901,$B$1,Data!$F$2:$F$901,$B$2) -> 5562 | D29: =C29+ROW()/1000000 -> 5562
A30: Face Roller | B30: Beauty | C30: =SUMIFS(Data!$K$2:$K$901,Data!$M$2:$M$901,"Delivered",Data!$G$2:$G$901,$A30,Data!$E$2:$E$901,$B$1,Data!$F$2:$F$901,$B$2) -> 1314 | D30: =C30+ROW()/1000000 -> 1314
A31: Canvas Tote | B31: Fashion | C31: =SUMIFS(Data!$K$2:$K$901,Data!$M$2:$M$901,"Delivered",Data!$G$2:$G$901,$A31,Data!$E$2:$E$901,$B$1,Data!$F$2:$F$901,$B$2) -> 2046 | D31: =C31+ROW()/1000000 -> 2046
A32: Sunglasses | B32: Fashion | C32: =SUMIFS(Data!$K$2:$K$901,Data!$M$2:$M$901,"Delivered",Data!$G$2:$G$901,$A32,Data!$E$2:$E$901,$B$1,Data!$F$2:$F$901,$B$2) -> 2940 | D32: =C32+ROW()/1000000 -> 2940
A33: Leather Wallet | B33: Fashion | C33: =SUMIFS(Data!$K$2:$K$901,Data!$M$2:$M$901,"Delivered",Data!$G$2:$G$901,$A33,Data!$E$2:$E$901,$B$1,Data!$F$2:$F$901,$B$2) -> 4230 | D33: =C33+ROW()/1000000 -> 4230
A34: Yoga Mat | B34: Fitness | C34: =SUMIFS(Data!$K$2:$K$901,Data!$M$2:$M$901,"Delivered",Data!$G$2:$G$901,$A34,Data!$E$2:$E$901,$B$1,Data!$F$2:$F$901,$B$2) -> 1770 | D34: =C34+ROW()/1000000 -> 1770
A35: Resistance Bands | B35: Fitness | C35: =SUMIFS(Data!$K$2:$K$901,Data!$M$2:$M$901,"Delivered",Data!$G$2:$G$901,$A35,Data!$E$2:$E$901,$B$1,Data!$F$2:$F$901,$B$2) -> 1408 | D35: =C35+ROW()/1000000 -> 1408
A36: Water Bottle | B36: Fitness | C36: =SUMIFS(Data!$K$2:$K$901,Data!$M$2:$M$901,"Delivered",Data!$G$2:$G$901,$A36,Data!$E$2:$E$901,$B$1,Data!$F$2:$F$901,$B$2) -> 1260 | D36: =C36+ROW()/1000000 -> 1260
A38: These tables feed the Dashboard charts. They recalculate when the Region and Category selectors change. Only Delivered orders count as revenue.
